Workbook

Sheet Legend
A1: Pilot recording sheet and Phase 1 gate (product spec section 22 Phase 1, Appendix F)
A3: TABS: Jobs (one row per job) | Gate (pass or fail, formulas) | Lists (reference prices and pay from spec section 16) | Example (synthetic values, with its own gate).
A4: Record every field for every job and review weekly (F.3). Active minutes = time the expert actually worked, not elapsed time.
A5: Contribution per job = price paid - refund - (expert pay + payment fee + review cost + other cost). Spec 16.4 assumes other costs at 14% of price plus review cost; here you record actuals.
A6: Delivery times are date and time in one time zone. Enter the SAME zone in all three date columns.
A7: On time = delivered at or before the promised delivery. Hours to delivery = delivered minus paid.
A8: Yellow = decision for the owner. Blue = input. Black = formula.
A9: Known spec conflicts shown on the Gate tab: revision threshold (20% vs 15%) and contribution threshold ($25 vs $30). This sheet uses section 22 (the Phase 1 gate) until the owner decides.
A10: Never enter client names or contact details.

Sheet Jobs
A1: Pilot recording sheet: one row per job
A2: Blue = type in. Black = formula. Capped pilot: 20 to 30 orders (spec F.3). 40 rows are formula-ready. Never type client names or contact details here. Use Job IDs.
A3: Job ID | B3: Tier | C3: Cover letter (Y/N) | D3: Expert ID | E3: Client region | F3: Paid at (date and time) | G3: Promised delivery (date and time) | H3: Delivered at (date and time) | I3: Price paid ($) | J3: Expert active minutes | K3: Questions asked | L3: Questions answered (count) | M3: Revision requested (Y/N) | N3: Revision reason | O3: Score before | P3: Score after | Q3: Client rating (1-5) | R3: Refund amount ($) | S3: Refund reason | T3: Expert pay ($) | U3: Payment fee ($) | V3: Review cost ($) | W3: Other cost ($) | X3: Fact-drift catches (count) | Y3: Privacy incident (Y/N) | Z3: Invented fact reached client (Y/N) | AA3: Notes | AB3: Hours to delivery | AC3: Hours late (0 if on time) | AD3: On time? (1/0) | AE3: Score change | AF3: Revision (1/0) | AG3: Refunded (1/0) | AH3: Total cost ($) | AI3: Net revenue ($) | AJ3: Contribution ($) | AK3: Contribution %
AB4: =IF(OR(F4="",H4=""),"",ROUND((H4-F4)*24,1)) | AC4: =IF(OR(G4="",H4=""),"",MAX(0,ROUND((H4-G4)*24,1))) | AD4: =IF(AC4="","",IF(AC4=0,1,0)) | AE4: =IF(OR(O4="",P4=""),"",P4-O4) | AF4: =IF(A4="","",IF(UPPER(M4)="Y",1,0)) | AG4: =IF(A4="","",IF(N(R4)>0,1,0)) | AH4: =IF(I4="","",N(T4)+N(U4)+N(V4)+N(W4)) | AI4: =IF(I4="","",I4-N(R4)) | AJ4: =IF(I4="","",AI4-AH4) | AK4: =IF(I4="","",IF(I4=0,"",AJ4/I4))
AB5: =IF(OR(F5="",H5=""),"",ROUND((H5-F5)*24,1)) | AC5: =IF(OR(G5="",H5=""),"",MAX(0,ROUND((H5-G5)*24,1))) | AD5: =IF(AC5="","",IF(AC5=0,1,0)) | AE5: =IF(OR(O5="",P5=""),"",P5-O5) | AF5: =IF(A5="","",IF(UPPER(M5)="Y",1,0)) | AG5: =IF(A5="","",IF(N(R5)>0,1,0)) | AH5: =IF(I5="","",N(T5)+N(U5)+N(V5)+N(W5)) | AI5: =IF(I5="","",I5-N(R5)) | AJ5: =IF(I5="","",AI5-AH5) | AK5: =IF(I5="","",IF(I5=0,"",AJ5/I5))
AB6: =IF(OR(F6="",H6=""),"",ROUND((H6-F6)*24,1)) | AC6: =IF(OR(G6="",H6=""),"",MAX(0,ROUND((H6-G6)*24,1))) | AD6: =IF(AC6="","",IF(AC6=0,1,0)) | AE6: =IF(OR(O6="",P6=""),"",P6-O6) | AF6: =IF(A6="","",IF(UPPER(M6)="Y",1,0)) | AG6: =IF(A6="","",IF(N(R6)>0,1,0)) | AH6: =IF(I6="","",N(T6)+N(U6)+N(V6)+N(W6)) | AI6: =IF(I6="","",I6-N(R6)) | AJ6: =IF(I6="","",AI6-AH6) | AK6: =IF(I6="","",IF(I6=0,"",AJ6/I6))
AB7: =IF(OR(F7="",H7=""),"",ROUND((H7-F7)*24,1)) | AC7: =IF(OR(G7="",H7=""),"",MAX(0,ROUND((H7-G7)*24,1))) | AD7: =IF(AC7="","",IF(AC7=0,1,0)) | AE7: =IF(OR(O7="",P7=""),"",P7-O7) | AF7: =IF(A7="","",IF(UPPER(M7)="Y",1,0)) | AG7: =IF(A7="","",IF(N(R7)>0,1,0)) | AH7: =IF(I7="","",N(T7)+N(U7)+N(V7)+N(W7)) | AI7: =IF(I7="","",I7-N(R7)) | AJ7: =IF(I7="","",AI7-AH7) | AK7: =IF(I7="","",IF(I7=0,"",AJ7/I7))
AB8: =IF(OR(F8="",H8=""),"",ROUND((H8-F8)*24,1)) | AC8: =IF(OR(G8="",H8=""),"",MAX(0,ROUND((H8-G8)*24,1))) | AD8: =IF(AC8="","",IF(AC8=0,1,0)) | AE8: =IF(OR(O8="",P8=""),"",P8-O8) | AF8: =IF(A8="","",IF(UPPER(M8)="Y",1,0)) | AG8: =IF(A8="","",IF(N(R8)>0,1,0)) | AH8: =IF(I8="","",N(T8)+N(U8)+N(V8)+N(W8)) | AI8: =IF(I8="","",I8-N(R8)) | AJ8: =IF(I8="","",AI8-AH8) | AK8: =IF(I8="","",IF(I8=0,"",AJ8/I8))
AB9: =IF(OR(F9="",H9=""),"",ROUND((H9-F9)*24,1)) | AC9: =IF(OR(G9="",H9=""),"",MAX(0,ROUND((H9-G9)*24,1))) | AD9: =IF(AC9="","",IF(AC9=0,1,0)) | AE9: =IF(OR(O9="",P9=""),"",P9-O9) | AF9: =IF(A9="","",IF(UPPER(M9)="Y",1,0)) | AG9: =IF(A9="","",IF(N(R9)>0,1,0)) | AH9: =IF(I9="","",N(T9)+N(U9)+N(V9)+N(W9)) | AI9: =IF(I9="","",I9-N(R9)) | AJ9: =IF(I9="","",AI9-AH9) | AK9: =IF(I9="","",IF(I9=0,"",AJ9/I9))
AB10: =IF(OR(F10="",H10=""),"",ROUND((H10-F10)*24,1)) | AC10: =IF(OR(G10="",H10=""),"",MAX(0,ROUND((H10-G10)*24,1))) | AD10: =IF(AC10="","",IF(AC10=0,1,0)) | AE10: =IF(OR(O10="",P10=""),"",P10-O10) | AF10: =IF(A10="","",IF(UPPER(M10)="Y",1,0)) | AG10: =IF(A10="","",IF(N(R10)>0,1,0)) | AH10: =IF(I10="","",N(T10)+N(U10)+N(V10)+N(W10)) | AI10: =IF(I10="","",I10-N(R10)) | AJ10: =IF(I10="","",AI10-AH10) | AK10: =IF(I10="","",IF(I10=0,"",AJ10/I10))
AB11: =IF(OR(F11="",H11=""),"",ROUND((H11-F11)*24,1)) | AC11: =IF(OR(G11="",H11=""),"",MAX(0,ROUND((H11-G11)*24,1))) | AD11: =IF(AC11="","",IF(AC11=0,1,0)) | AE11: =IF(OR(O11="",P11=""),"",P11-O11) | AF11: =IF(A11="","",IF(UPPER(M11)="Y",1,0)) | AG11: =IF(A11="","",IF(N(R11)>0,1,0)) | AH11: =IF(I11="","",N(T11)+N(U11)+N(V11)+N(W11)) | AI11: =IF(I11="","",I11-N(R11)) | AJ11: =IF(I11="","",AI11-AH11) | AK11: =IF(I11="","",IF(I11=0,"",AJ11/I11))
AB12: =IF(OR(F12="",H12=""),"",ROUND((H12-F12)*24,1)) | AC12: =IF(OR(G12="",H12=""),"",MAX(0,ROUND((H12-G12)*24,1))) | AD12: =IF(AC12="","",IF(AC12=0,1,0)) | AE12: =IF(OR(O12="",P12=""),"",P12-O12) | AF12: =IF(A12="","",IF(UPPER(M12)="Y",1,0)) | AG12: =IF(A12="","",IF(N(R12)>0,1,0)) | AH12: =IF(I12="","",N(T12)+N(U12)+N(V12)+N(W12)) | AI12: =IF(I12="","",I12-N(R12)) | AJ12: =IF(I12="","",AI12-AH12) | AK12: =IF(I12="","",IF(I12=0,"",AJ12/I12))
AB13: =IF(OR(F13="",H13=""),"",ROUND((H13-F13)*24,1)) | AC13: =IF(OR(G13="",H13=""),"",MAX(0,ROUND((H13-G13)*24,1))) | AD13: =IF(AC13="","",IF(AC13=0,1,0)) | AE13: =IF(OR(O13="",P13=""),"",P13-O13) | AF13: =IF(A13="","",IF(UPPER(M13)="Y",1,0)) | AG13: =IF(A13="","",IF(N(R13)>0,1,0)) | AH13: =IF(I13="","",N(T13)+N(U13)+N(V13)+N(W13)) | AI13: =IF(I13="","",I13-N(R13)) | AJ13: =IF(I13="","",AI13-AH13) | AK13: =IF(I13="","",IF(I13=0,"",AJ13/I13))
AB14: =IF(OR(F14="",H14=""),"",ROUND((H14-F14)*24,1)) | AC14: =IF(OR(G14="",H14=""),"",MAX(0,ROUND((H14-G14)*24,1))) | AD14: =IF(AC14="","",IF(AC14=0,1,0)) | AE14: =IF(OR(O14="",P14=""),"",P14-O14) | AF14: =IF(A14="","",IF(UPPER(M14)="Y",1,0)) | AG14: =IF(A14="","",IF(N(R14)>0,1,0)) | AH14: =IF(I14="","",N(T14)+N(U14)+N(V14)+N(W14)) | AI14: =IF(I14="","",I14-N(R14)) | AJ14: =IF(I14="","",AI14-AH14) | AK14: =IF(I14="","",IF(I14=0,"",AJ14/I14))
AB15: =IF(OR(F15="",H15=""),"",ROUND((H15-F15)*24,1)) | AC15: =IF(OR(G15="",H15=""),"",MAX(0,ROUND((H15-G15)*24,1))) | AD15: =IF(AC15="","",IF(AC15=0,1,0)) | AE15: =IF(OR(O15="",P15=""),"",P15-O15) | AF15: =IF(A15="","",IF(UPPER(M15)="Y",1,0)) | AG15: =IF(A15="","",IF(N(R15)>0,1,0)) | AH15: =IF(I15="","",N(T15)+N(U15)+N(V15)+N(W15)) | AI15: =IF(I15="","",I15-N(R15)) | AJ15: =IF(I15="","",AI15-AH15) | AK15: =IF(I15="","",IF(I15=0,"",AJ15/I15))
... AB43: =IF(OR(F43="",H43=""),"",ROUND((H43-F43)*24,1)) | AC43: =IF(OR(G43="",H43=""),"",MAX(0,ROUND((H43-G43)*24,1))) | AD43: =IF(AC43="","",IF(AC43=0,1,0)) | AE43: =IF(OR(O43="",P43=""),"",P43-O43) | AF43: =IF(A43="","",IF(UPPER(M43)="Y",1,0)) | AG43: =IF(A43="","",IF(N(R43)>0,1,0)) | AH43: =IF(I43="","",N(T43)+N(U43)+N(V43)+N(W43)) | AI43: =IF(I43="","",I43-N(R43)) | AJ43: =IF(I43="","",AI43-AH43) | AK43: =IF(I43="","",IF(I43=0,"",AJ43/I43))

Sheet Gate
A1: Phase 1 gate: pass or fail
A2: Thresholds are the product spec section 22 (Phase 1) gate. They are inputs: change a blue value only if you decide to. Section 23 lists different targets for two items (see column F).
A4: Measure | B4: Result | C4: Threshold (input) | D4: Test | E4: Pass? | F4: Note / spec reference
A5: Paid orders (jobs with a price) | B5: =COUNT(Jobs!$I$4:$I$43) -> 0 | C5: 20 | D5: >= | E5: =IF(B5="","",IF(B5>=C5,"PASS","FAIL")) -> FAIL | F5: Spec 22: 20 or more paid orders. Pilot cap is 20 to 30 (F.3).
A6: On-time delivery % | B6: =IF(COUNT(Jobs!$AD$4:$AD$43)=0,"",SUM(Jobs!$AD$4:$AD$43)/COUNT(Jobs!$AD$4:$AD$43)) | C6: 0.95 | D6: >= | E6: =IF(B6="","",IF(B6>=C6,"PASS","FAIL")) | F6: Spec 22: at least 95%.
A7: Average client rating | B7: =IF(COUNT(Jobs!$Q$4:$Q$43)=0,"",AVERAGE(Jobs!$Q$4:$Q$43)) | C7: 4.5 | D7: >= | E7: =IF(B7="","",IF(B7>=C7,"PASS","FAIL")) | F7: Spec 22: at least 4.5.
A8: Revision rate | B8: =IF(COUNT(Jobs!$AF$4:$AF$43)=0,"",SUM(Jobs!$AF$4:$AF$43)/COUNT(Jobs!$AF$4:$AF$43)) | C8: 0.2 | D8: < | E8: =IF(B8="","",IF(B8<C8,"PASS","FAIL")) | F8: Spec 22: under 20%. CONFLICT: section 23 target says under 15%. Owner to choose.
A9: Refund rate (jobs with a refund / paid jobs) | B9: =IF(COUNT(Jobs!$AG$4:$AG$43)=0,"",SUM(Jobs!$AG$4:$AG$43)/COUNT(Jobs!$AG$4:$AG$43)) | C9: 0.08 | D9: < | E9: =IF(B9="","",IF(B9<C9,"PASS","FAIL")) | F9: Spec 22: under 8%. Counted by job; spec does not say count or value. Owner to confirm.
A10: Average contribution per job ($) | B10: =IF(COUNT(Jobs!$AJ$4:$AJ$43)=0,"",AVERAGE(Jobs!$AJ$4:$AJ$43)) | C10: 25 | D10: >= | E10: =IF(B10="","",IF(B10>=C10,"PASS","FAIL")) | F10: Spec 22: at least $25. CONFLICT: section 23 target says $30. Owner to choose.
A11: Contribution % (total contribution / total price paid) | B11: =IF(SUM(Jobs!$I$4:$I$43)=0,"",SUM(Jobs!$AJ$4:$AJ$43)/SUM(Jobs!$I$4:$I$43)) | C11: 0.25 | D11: >= | E11: =IF(B11="","",IF(B11>=C11,"PASS","FAIL")) | F11: Spec 22: at least 25%.
A12: Average expert active minutes | B12: =IF(COUNT(Jobs!$J$4:$J$43)=0,"",AVERAGE(Jobs!$J$4:$J$43)) | C12: 75 | D12: <= | E12: =IF(B12="","",IF(B12<=C12,"PASS","FAIL")) | F12: Spec 22: measured expert time at most 75 minutes.
A13: Experts willing to continue at the pay (1 = yes, 0 = no) | C13: 1 | D13: >= | E13: =IF(B13="","",IF(B13>=C13,"PASS","FAIL")) | F13: Enter after asking every pilot expert. Blank until then.
A15: PHASE 1 GATE RESULT | B15: =IF(COUNTIF(E5:E13,"")>0,"Incomplete: "&COUNTIF(E5:E13,"")&" measure(s) missing",IF(COUNTIF(E5:E13,"FAIL")=0,"PASS","FAIL")) -> Incomplete: 8 measure(s) missing
A17: KILL OR ADJUST CHECKS (spec 22)
A18: Average expert minutes over 120 (raise price or move buyers to polish) | B18: =IF(B12="","",IF(B12>120,"TRIGGERED","clear"))
A19: Refund rate over 15% (stop and fix quality) | B19: =IF(B9="","",IF(B9>0.15,"TRIGGERED","clear"))
A20: Average rating under 4.0 (stop and fix quality) | B20: =IF(B7="","",IF(B7<4,"TRIGGERED","clear"))
A21: Privacy incident recorded (spec F.3: stop at once) | B21: =IF(COUNTIF(Jobs!$Y$4:$Y$43,"Y")>0,"STOP","clear") -> clear
A22: Invented fact reached a client (spec F.3: stop at once) | B22: =IF(COUNTIF(Jobs!$Z$4:$Z$43,"Y")>0,"STOP","clear") -> clear
A24: PILOT QUESTIONS (F.1): descriptive
A25: Fact-drift catches (total) | B25: =SUM(Jobs!$X$4:$X$43) -> 0
A26: Questions asked per job (average) | B26: =IF(COUNT(Jobs!$K$4:$K$43)=0,"",AVERAGE(Jobs!$K$4:$K$43))
A27: Average score gain (after minus before) | B27: =IF(COUNT(Jobs!$AE$4:$AE$43)=0,"",AVERAGE(Jobs!$AE$4:$AE$43))
A28: Average hours to delivery | B28: =IF(COUNT(Jobs!$AB$4:$AB$43)=0,"",AVERAGE(Jobs!$AB$4:$AB$43))

Sheet Lists
A1: Reference from product spec v2.2 section 16 (headline prices and Standard payouts). For checking, not used in formulas.
A3: Tier | B3: Spec price ($) | C3: Spec Standard payout ($) | D3: Spec timing
A4: Polish | B4: 59 | C4: 25 | D4: Turnaround not defined in spec (flagged)
A5: Rewrite 7d | B5: 89 | C5: 50 | D5: 7 days
A6: Rewrite 48h | B6: 119 | C6: 70 | D6: 48 hours
A7: Rewrite 24h | B7: 149 | C7: 90 | D7: 24 hours (only when founder can rescue)
A8: Cover letter add-on | B8: 29 | C8: 18

Sheet Example (synthetic)
A1: Pilot recording sheet: one row per job (EXAMPLE, synthetic values)
A2: Blue = type in. Black = formula. Capped pilot: 20 to 30 orders (spec F.3). 40 rows are formula-ready. Never type client names or contact details here. Use Job IDs.
A3: Job ID | B3: Tier | C3: Cover letter (Y/N) | D3: Expert ID | E3: Client region | F3: Paid at (date and time) | G3: Promised delivery (date and time) | H3: Delivered at (date and time) | I3: Price paid ($) | J3: Expert active minutes | K3: Questions asked | L3: Questions answered (count) | M3: Revision requested (Y/N) | N3: Revision reason | O3: Score before | P3: Score after | Q3: Client rating (1-5) | R3: Refund amount ($) | S3: Refund reason | T3: Expert pay ($) | U3: Payment fee ($) | V3: Review cost ($) | W3: Other cost ($) | X3: Fact-drift catches (count) | Y3: Privacy incident (Y/N) | Z3: Invented fact reached client (Y/N) | AA3: Notes | AB3: Hours to delivery | AC3: Hours late (0 if on time) | AD3: On time? (1/0) | AE3: Score change | AF3: Revision (1/0) | AG3: Refunded (1/0) | AH3: Total cost ($) | AI3: Net revenue ($) | AJ3: Contribution ($) | AK3: Contribution %
A4: J-001 | B4: Rewrite 7d | C4: N | D4: E-01 | E4: US | F4: 46328.375 | G4: 46335.375 | H4: 46332.646 | I4: 89 | J4: 62 | K4: 1 | L4: 1 | M4: N | O4: 58 | P4: 84 | Q4: 5 | T4: 50 | U4: 3.5 | V4: 5 | W4: 2 | X4: 1 | Y4: N | Z4: N | AB4: =IF(OR(F4="",H4=""),"",ROUND((H4-F4)*24,1)) -> 102.5 | AC4: =IF(OR(G4="",H4=""),"",MAX(0,ROUND((H4-G4)*24,1))) -> 0 | AD4: =IF(AC4="","",IF(AC4=0,1,0)) -> 1 | AE4: =IF(OR(O4="",P4=""),"",P4-O4) -> 26 | AF4: =IF(A4="","",IF(UPPER(M4)="Y",1,0)) -> 0 | AG4: =IF(A4="","",IF(N(R4)>0,1,0)) -> 0 | AH4: =IF(I4="","",N(T4)+N(U4)+N(V4)+N(W4)) -> 60.5 | AI4: =IF(I4="","",I4-N(R4)) -> 89 | AJ4: =IF(I4="","",AI4-AH4) -> 28.5 | AK4: =IF(I4="","",IF(I4=0,"",AJ4/I4)) -> 0.32022472
A5: J-002 | B5: Rewrite 48h | C5: Y | D5: E-02 | E5: UK | F5: 46329.417 | G5: 46331.417 | H5: 46331.542 | I5: 148 | J5: 95 | K5: 2 | L5: 2 | M5: Y | N5: Wanted a different summary emphasis | O5: 51 | P5: 80 | Q5: 4 | T5: 92.4 | U5: 5 | V5: 5 | W5: 3 | X5: 0 | Y5: N | Z5: N | AA5: 3 hours late (credit applies per spec 6.6) | AB5: =IF(OR(F5="",H5=""),"",ROUND((H5-F5)*24,1)) -> 51 | AC5: =IF(OR(G5="",H5=""),"",MAX(0,ROUND((H5-G5)*24,1))) -> 3 | AD5: =IF(AC5="","",IF(AC5=0,1,0)) -> 0 | AE5: =IF(OR(O5="",P5=""),"",P5-O5) -> 29 | AF5: =IF(A5="","",IF(UPPER(M5)="Y",1,0)) -> 1 | AG5: =IF(A5="","",IF(N(R5)>0,1,0)) -> 0 | AH5: =IF(I5="","",N(T5)+N(U5)+N(V5)+N(W5)) -> 105.4 | AI5: =IF(I5="","",I5-N(R5)) -> 148 | AJ5: =IF(I5="","",AI5-AH5) -> 42.6 | AK5: =IF(I5="","",IF(I5=0,"",AJ5/I5)) -> 0.28783784
A6: J-003 | B6: Polish | C6: N | D6: E-01 | E6: KE | F6: 46330.333 | G6: 46332.333 | H6: 46331.5 | I6: 59 | J6: 28 | K6: 0 | L6: 0 | M6: N | O6: 66 | P6: 82 | Q6: 5 | R6: 0 | T6: 25 | U6: 2.5 | V6: 1 | W6: 1 | Y6: N | Z6: N | AA6: Polish promised-delivery shown as an example only: spec defines no polish deadline | AB6: =IF(OR(F6="",H6=""),"",ROUND((H6-F6)*24,1)) -> 28 | AC6: =IF(OR(G6="",H6=""),"",MAX(0,ROUND((H6-G6)*24,1))) -> 0 | AD6: =IF(AC6="","",IF(AC6=0,1,0)) -> 1 | AE6: =IF(OR(O6="",P6=""),"",P6-O6) -> 16 | AF6: =IF(A6="","",IF(UPPER(M6)="Y",1,0)) -> 0 | AG6: =IF(A6="","",IF(N(R6)>0,1,0)) -> 0 | AH6: =IF(I6="","",N(T6)+N(U6)+N(V6)+N(W6)) -> 29.5 | AI6: =IF(I6="","",I6-N(R6)) -> 59 | AJ6: =IF(I6="","",AI6-AH6) -> 29.5 | AK6: =IF(I6="","",IF(I6=0,"",AJ6/I6)) -> 0.5
AB7: =IF(OR(F7="",H7=""),"",ROUND((H7-F7)*24,1)) | AC7: =IF(OR(G7="",H7=""),"",MAX(0,ROUND((H7-G7)*24,1))) | AD7: =IF(AC7="","",IF(AC7=0,1,0)) | AE7: =IF(OR(O7="",P7=""),"",P7-O7) | AF7: =IF(A7="","",IF(UPPER(M7)="Y",1,0)) | AG7: =IF(A7="","",IF(N(R7)>0,1,0)) | AH7: =IF(I7="","",N(T7)+N(U7)+N(V7)+N(W7)) | AI7: =IF(I7="","",I7-N(R7)) | AJ7: =IF(I7="","",AI7-AH7) | AK7: =IF(I7="","",IF(I7=0,"",AJ7/I7))
AB8: =IF(OR(F8="",H8=""),"",ROUND((H8-F8)*24,1)) | AC8: =IF(OR(G8="",H8=""),"",MAX(0,ROUND((H8-G8)*24,1))) | AD8: =IF(AC8="","",IF(AC8=0,1,0)) | AE8: =IF(OR(O8="",P8=""),"",P8-O8) | AF8: =IF(A8="","",IF(UPPER(M8)="Y",1,0)) | AG8: =IF(A8="","",IF(N(R8)>0,1,0)) | AH8: =IF(I8="","",N(T8)+N(U8)+N(V8)+N(W8)) | AI8: =IF(I8="","",I8-N(R8)) | AJ8: =IF(I8="","",AI8-AH8) | AK8: =IF(I8="","",IF(I8=0,"",AJ8/I8))
AB9: =IF(OR(F9="",H9=""),"",ROUND((H9-F9)*24,1)) | AC9: =IF(OR(G9="",H9=""),"",MAX(0,ROUND((H9-G9)*24,1))) | AD9: =IF(AC9="","",IF(AC9=0,1,0)) | AE9: =IF(OR(O9="",P9=""),"",P9-O9) | AF9: =IF(A9="","",IF(UPPER(M9)="Y",1,0)) | AG9: =IF(A9="","",IF(N(R9)>0,1,0)) | AH9: =IF(I9="","",N(T9)+N(U9)+N(V9)+N(W9)) | AI9: =IF(I9="","",I9-N(R9)) | AJ9: =IF(I9="","",AI9-AH9) | AK9: =IF(I9="","",IF(I9=0,"",AJ9/I9))
AB10: =IF(OR(F10="",H10=""),"",ROUND((H10-F10)*24,1)) | AC10: =IF(OR(G10="",H10=""),"",MAX(0,ROUND((H10-G10)*24,1))) | AD10: =IF(AC10="","",IF(AC10=0,1,0)) | AE10: =IF(OR(O10="",P10=""),"",P10-O10) | AF10: =IF(A10="","",IF(UPPER(M10)="Y",1,0)) | AG10: =IF(A10="","",IF(N(R10)>0,1,0)) | AH10: =IF(I10="","",N(T10)+N(U10)+N(V10)+N(W10)) | AI10: =IF(I10="","",I10-N(R10)) | AJ10: =IF(I10="","",AI10-AH10) | AK10: =IF(I10="","",IF(I10=0,"",AJ10/I10))
AB11: =IF(OR(F11="",H11=""),"",ROUND((H11-F11)*24,1)) | AC11: =IF(OR(G11="",H11=""),"",MAX(0,ROUND((H11-G11)*24,1))) | AD11: =IF(AC11="","",IF(AC11=0,1,0)) | AE11: =IF(OR(O11="",P11=""),"",P11-O11) | AF11: =IF(A11="","",IF(UPPER(M11)="Y",1,0)) | AG11: =IF(A11="","",IF(N(R11)>0,1,0)) | AH11: =IF(I11="","",N(T11)+N(U11)+N(V11)+N(W11)) | AI11: =IF(I11="","",I11-N(R11)) | AJ11: =IF(I11="","",AI11-AH11) | AK11: =IF(I11="","",IF(I11=0,"",AJ11/I11))
AB12: =IF(OR(F12="",H12=""),"",ROUND((H12-F12)*24,1)) | AC12: =IF(OR(G12="",H12=""),"",MAX(0,ROUND((H12-G12)*24,1))) | AD12: =IF(AC12="","",IF(AC12=0,1,0)) | AE12: =IF(OR(O12="",P12=""),"",P12-O12) | AF12: =IF(A12="","",IF(UPPER(M12)="Y",1,0)) | AG12: =IF(A12="","",IF(N(R12)>0,1,0)) | AH12: =IF(I12="","",N(T12)+N(U12)+N(V12)+N(W12)) | AI12: =IF(I12="","",I12-N(R12)) | AJ12: =IF(I12="","",AI12-AH12) | AK12: =IF(I12="","",IF(I12=0,"",AJ12/I12))
AB13: =IF(OR(F13="",H13=""),"",ROUND((H13-F13)*24,1)) | AC13: =IF(OR(G13="",H13=""),"",MAX(0,ROUND((H13-G13)*24,1))) | AD13: =IF(AC13="","",IF(AC13=0,1,0)) | AE13: =IF(OR(O13="",P13=""),"",P13-O13) | AF13: =IF(A13="","",IF(UPPER(M13)="Y",1,0)) | AG13: =IF(A13="","",IF(N(R13)>0,1,0)) | AH13: =IF(I13="","",N(T13)+N(U13)+N(V13)+N(W13)) | AI13: =IF(I13="","",I13-N(R13)) | AJ13: =IF(I13="","",AI13-AH13) | AK13: =IF(I13="","",IF(I13=0,"",AJ13/I13))
AB14: =IF(OR(F14="",H14=""),"",ROUND((H14-F14)*24,1)) | AC14: =IF(OR(G14="",H14=""),"",MAX(0,ROUND((H14-G14)*24,1))) | AD14: =IF(AC14="","",IF(AC14=0,1,0)) | AE14: =IF(OR(O14="",P14=""),"",P14-O14) | AF14: =IF(A14="","",IF(UPPER(M14)="Y",1,0)) | AG14: =IF(A14="","",IF(N(R14)>0,1,0)) | AH14: =IF(I14="","",N(T14)+N(U14)+N(V14)+N(W14)) | AI14: =IF(I14="","",I14-N(R14)) | AJ14: =IF(I14="","",AI14-AH14) | AK14: =IF(I14="","",IF(I14=0,"",AJ14/I14))
AB15: =IF(OR(F15="",H15=""),"",ROUND((H15-F15)*24,1)) | AC15: =IF(OR(G15="",H15=""),"",MAX(0,ROUND((H15-G15)*24,1))) | AD15: =IF(AC15="","",IF(AC15=0,1,0)) | AE15: =IF(OR(O15="",P15=""),"",P15-O15) | AF15: =IF(A15="","",IF(UPPER(M15)="Y",1,0)) | AG15: =IF(A15="","",IF(N(R15)>0,1,0)) | AH15: =IF(I15="","",N(T15)+N(U15)+N(V15)+N(W15)) | AI15: =IF(I15="","",I15-N(R15)) | AJ15: =IF(I15="","",AI15-AH15) | AK15: =IF(I15="","",IF(I15=0,"",AJ15/I15))
AB16: =IF(OR(F16="",H16=""),"",ROUND((H16-F16)*24,1)) | AC16: =IF(OR(G16="",H16=""),"",MAX(0,ROUND((H16-G16)*24,1))) | AD16: =IF(AC16="","",IF(AC16=0,1,0)) | AE16: =IF(OR(O16="",P16=""),"",P16-O16) | AF16: =IF(A16="","",IF(UPPER(M16)="Y",1,0)) | AG16: =IF(A16="","",IF(N(R16)>0,1,0)) | AH16: =IF(I16="","",N(T16)+N(U16)+N(V16)+N(W16)) | AI16: =IF(I16="","",I16-N(R16)) | AJ16: =IF(I16="","",AI16-AH16) | AK16: =IF(I16="","",IF(I16=0,"",AJ16/I16))
AB17: =IF(OR(F17="",H17=""),"",ROUND((H17-F17)*24,1)) | AC17: =IF(OR(G17="",H17=""),"",MAX(0,ROUND((H17-G17)*24,1))) | AD17: =IF(AC17="","",IF(AC17=0,1,0)) | AE17: =IF(OR(O17="",P17=""),"",P17-O17) | AF17: =IF(A17="","",IF(UPPER(M17)="Y",1,0)) | AG17: =IF(A17="","",IF(N(R17)>0,1,0)) | AH17: =IF(I17="","",N(T17)+N(U17)+N(V17)+N(W17)) | AI17: =IF(I17="","",I17-N(R17)) | AJ17: =IF(I17="","",AI17-AH17) | AK17: =IF(I17="","",IF(I17=0,"",AJ17/I17))
AB18: =IF(OR(F18="",H18=""),"",ROUND((H18-F18)*24,1)) | AC18: =IF(OR(G18="",H18=""),"",MAX(0,ROUND((H18-G18)*24,1))) | AD18: =IF(AC18="","",IF(AC18=0,1,0)) | AE18: =IF(OR(O18="",P18=""),"",P18-O18) | AF18: =IF(A18="","",IF(UPPER(M18)="Y",1,0)) | AG18: =IF(A18="","",IF(N(R18)>0,1,0)) | AH18: =IF(I18="","",N(T18)+N(U18)+N(V18)+N(W18)) | AI18: =IF(I18="","",I18-N(R18)) | AJ18: =IF(I18="","",AI18-AH18) | AK18: =IF(I18="","",IF(I18=0,"",AJ18/I18))
... AB43: =IF(OR(F43="",H43=""),"",ROUND((H43-F43)*24,1)) | AC43: =IF(OR(G43="",H43=""),"",MAX(0,ROUND((H43-G43)*24,1))) | AD43: =IF(AC43="","",IF(AC43=0,1,0)) | AE43: =IF(OR(O43="",P43=""),"",P43-O43) | AF43: =IF(A43="","",IF(UPPER(M43)="Y",1,0)) | AG43: =IF(A43="","",IF(N(R43)>0,1,0)) | AH43: =IF(I43="","",N(T43)+N(U43)+N(V43)+N(W43)) | AI43: =IF(I43="","",I43-N(R43)) | AJ43: =IF(I43="","",AI43-AH43) | AK43: =IF(I43="","",IF(I43=0,"",AJ43/I43))

Sheet Example gate
A1: Phase 1 gate: pass or fail
A2: Thresholds are the product spec section 22 (Phase 1) gate. They are inputs: change a blue value only if you decide to. Section 23 lists different targets for two items (see column F).
A4: Measure | B4: Result | C4: Threshold (input) | D4: Test | E4: Pass? | F4: Note / spec reference
A5: Paid orders (jobs with a price) | B5: =COUNT('Example (synthetic)'!$I$4:$I$43) -> 3 | C5: 20 | D5: >= | E5: =IF(B5="","",IF(B5>=C5,"PASS","FAIL")) -> FAIL | F5: Spec 22: 20 or more paid orders. Pilot cap is 20 to 30 (F.3).
A6: On-time delivery % | B6: =IF(COUNT('Example (synthetic)'!$AD$4:$AD$43)=0,"",SUM('Example (synthetic)'!$AD$4:$AD$43)/COUNT('Example (synthetic)'!$AD$4:$AD$43)) -> 0.66666667 | C6: 0.95 | D6: >= | E6: =IF(B6="","",IF(B6>=C6,"PASS","FAIL")) -> FAIL | F6: Spec 22: at least 95%.
A7: Average client rating | B7: =IF(COUNT('Example (synthetic)'!$Q$4:$Q$43)=0,"",AVERAGE('Example (synthetic)'!$Q$4:$Q$43)) -> 4.6666667 | C7: 4.5 | D7: >= | E7: =IF(B7="","",IF(B7>=C7,"PASS","FAIL")) -> PASS | F7: Spec 22: at least 4.5.
A8: Revision rate | B8: =IF(COUNT('Example (synthetic)'!$AF$4:$AF$43)=0,"",SUM('Example (synthetic)'!$AF$4:$AF$43)/COUNT('Example (synthetic)'!$AF$4:$AF$43)) -> 0.33333333 | C8: 0.2 | D8: < | E8: =IF(B8="","",IF(B8<C8,"PASS","FAIL")) -> FAIL | F8: Spec 22: under 20%. CONFLICT: section 23 target says under 15%. Owner to choose.
A9: Refund rate (jobs with a refund / paid jobs) | B9: =IF(COUNT('Example (synthetic)'!$AG$4:$AG$43)=0,"",SUM('Example (synthetic)'!$AG$4:$AG$43)/COUNT('Example (synthetic)'!$AG$4:$AG$43)) -> 0 | C9: 0.08 | D9: < | E9: =IF(B9="","",IF(B9<C9,"PASS","FAIL")) -> PASS | F9: Spec 22: under 8%. Counted by job; spec does not say count or value. Owner to confirm.
A10: Average contribution per job ($) | B10: =IF(COUNT('Example (synthetic)'!$AJ$4:$AJ$43)=0,"",AVERAGE('Example (synthetic)'!$AJ$4:$AJ$43)) -> 33.533333 | C10: 25 | D10: >= | E10: =IF(B10="","",IF(B10>=C10,"PASS","FAIL")) -> PASS | F10: Spec 22: at least $25. CONFLICT: section 23 target says $30. Owner to choose.
A11: Contribution % (total contribution / total price paid) | B11: =IF(SUM('Example (synthetic)'!$I$4:$I$43)=0,"",SUM('Example (synthetic)'!$AJ$4:$AJ$43)/SUM('Example (synthetic)'!$I$4:$I$43)) -> 0.33986486 | C11: 0.25 | D11: >= | E11: =IF(B11="","",IF(B11>=C11,"PASS","FAIL")) -> PASS | F11: Spec 22: at least 25%.
A12: Average expert active minutes | B12: =IF(COUNT('Example (synthetic)'!$J$4:$J$43)=0,"",AVERAGE('Example (synthetic)'!$J$4:$J$43)) -> 61.666667 | C12: 75 | D12: <= | E12: =IF(B12="","",IF(B12<=C12,"PASS","FAIL")) -> PASS | F12: Spec 22: measured expert time at most 75 minutes.
A13: Experts willing to continue at the pay (1 = yes, 0 = no) | C13: 1 | D13: >= | E13: =IF(B13="","",IF(B13>=C13,"PASS","FAIL")) | F13: Enter after asking every pilot expert. Blank until then.
A15: PHASE 1 GATE RESULT | B15: =IF(COUNTIF(E5:E13,"")>0,"Incomplete: "&COUNTIF(E5:E13,"")&" measure(s) missing",IF(COUNTIF(E5:E13,"FAIL")=0,"PASS","FAIL")) -> Incomplete: 1 measure(s) missing
A17: KILL OR ADJUST CHECKS (spec 22)
A18: Average expert minutes over 120 (raise price or move buyers to polish) | B18: =IF(B12="","",IF(B12>120,"TRIGGERED","clear")) -> clear
A19: Refund rate over 15% (stop and fix quality) | B19: =IF(B9="","",IF(B9>0.15,"TRIGGERED","clear")) -> clear
A20: Average rating under 4.0 (stop and fix quality) | B20: =IF(B7="","",IF(B7<4,"TRIGGERED","clear")) -> clear
A21: Privacy incident recorded (spec F.3: stop at once) | B21: =IF(COUNTIF('Example (synthetic)'!$Y$4:$Y$43,"Y")>0,"STOP","clear") -> clear
A22: Invented fact reached a client (spec F.3: stop at once) | B22: =IF(COUNTIF('Example (synthetic)'!$Z$4:$Z$43,"Y")>0,"STOP","clear") -> clear
A24: PILOT QUESTIONS (F.1): descriptive
A25: Fact-drift catches (total) | B25: =SUM('Example (synthetic)'!$X$4:$X$43) -> 1
A26: Questions asked per job (average) | B26: =IF(COUNT('Example (synthetic)'!$K$4:$K$43)=0,"",AVERAGE('Example (synthetic)'!$K$4:$K$43)) -> 1
A27: Average score gain (after minus before) | B27: =IF(COUNT('Example (synthetic)'!$AE$4:$AE$43)=0,"",AVERAGE('Example (synthetic)'!$AE$4:$AE$43)) -> 23.666667
A28: Average hours to delivery | B28: =IF(COUNT('Example (synthetic)'!$AB$4:$AB$43)=0,"",AVERAGE('Example (synthetic)'!$AB$4:$AB$43)) -> 60.5
